<?xml version="1.0" encoding="utf-8" ?>
<Patch>
  <Operation Class="PatchOperationReplace">
    <xpath>/Defs/ThingDef[defName = "ToolCabinet"]/costList</xpath>
    <value>
		<costList>
			<MedTimes_CraftingTools>10</MedTimes_CraftingTools>
			<Steel>65</Steel>
		</costList>
    </value>
  </Operation>
  
  <Operation Class="PatchOperationRemove">
    <xpath>/Defs/ThingDef[defName = "SimpleResearchBench"]/costList/Steel</xpath>
  </Operation>
  
  <Operation Class="PatchOperationAdd">
    <xpath>/Defs/ThingDef[defName = "SimpleResearchBench"]/costList</xpath>
	<value>
		<MedTimes_Resource_PaperSheets>60</MedTimes_Resource_PaperSheets>
		<MedTimes_Resource_Glass>15</MedTimes_Resource_Glass>
	</value>
  </Operation>
  
	<Operation Class="PatchOperationReplace">
		<xpath>/Defs/ThingDef[defName = "ElectricSmithy"]/researchPrerequisites</xpath>
		<value>
			<researchPrerequisites>
				<li>MedTimes_Mechanization</li>
				<li>Smithing</li>
			</researchPrerequisites>
		</value>
	</Operation>
	
	<Operation Class="PatchOperationReplace">
		<xpath>/Defs/ThingDef[defName = "ElectricTailoringBench"]/researchPrerequisites</xpath>
		<value>
			<researchPrerequisites>
			  <li>ComplexClothing</li>
			  <li>MedTimes_Mechanization</li>
			</researchPrerequisites>
		</value>
	</Operation>
  
  
	<Operation Class="PatchOperationReplace">
		<xpath>/Defs/ThingDef[defName="HiTechResearchBench"]/researchPrerequisites</xpath>
		<value>
			<researchPrerequisites>
			  <li>IndTimes_PrecisionComputing</li>
			</researchPrerequisites>
		</value>
	</Operation>
	
	<Operation Class="PatchOperationReplace">
		<xpath>/Defs/ThingDef[defName="HiTechResearchBench"]/costList</xpath>
		<value>
			<costList>
			  <Steel>60</Steel>
			  <MedTimes_Resource_Glass>20</MedTimes_Resource_Glass>
			  <ComponentIndustrial>10</ComponentIndustrial>
			</costList>
		</value>
	</Operation>
  
</Patch>