<?xml version="1.0" encoding="UTF-8"?>
<Defs>
	<!-- <></> -->
	<!-- TMM_Hair_ -->
	<!-- TODO: this will all need a rewrite eventually -->



	<!-- <texPath>Modules/Pawns/Hair/Media/Games/</texPath> -->
	<!-- <texPath>Modules/Pawns/Hair/Media/Movies/</texPath> -->
	<!-- <texPath>Modules/Pawns/Hair/Media/TV/</texPath> -->


	<!-- GAMES -->
		<!-- ADA -->
			<HairDef>
				<label>Ada</label>
				<styleGender>Female</styleGender>
				<texPath>Modules/Pawns/Hair/Media/Games/Ada/Ada</texPath>
				<defName>TMM_Hair_Ada</defName>
				<category>Urban</category>
				<hairTags>
					<li>Urban</li>
					<li>Rural</li>
				</hairTags>
			</HairDef>
		<!-- BIG BOSS -->
			<HairDef>
				<label>Big Boss</label>
				<styleGender>Male</styleGender>
				<texPath>Modules/Pawns/Hair/Media/Games/BigBoss/BigBoss</texPath>
				<defName>TMM_Hair_BigBoss</defName>
				<category>Urban</category>
				<hairTags>
					<li>Urban</li>
					<li>Rural</li>
				</hairTags>
			</HairDef>
		<!-- BOOKER -->
			<HairDef>
				<label>Booker</label>
				<styleGender>Male</styleGender>
				<texPath>Modules/Pawns/Hair/Media/Games/Booker/Booker</texPath>
				<defName>TMM_Hair_Booker</defName>
				<category>Urban</category>
				<hairTags>
					<li>Urban</li>
					<li>Rural</li>
				</hairTags>
			</HairDef>
		<!-- CARLOS -->
			<HairDef>
				<label>Carlos</label>
				<styleGender>Male</styleGender>
				<texPath>Modules/Pawns/Hair/Media/Games/Carlos/Carlos</texPath>
				<defName>TMM_Hair_Carlos</defName>
				<category>Urban</category>
				<hairTags>
					<li>Urban</li>
					<li>Rural</li>
					<li>Punk</li>
				</hairTags>
			</HairDef>
		<!-- CASSIE -->
			<HairDef>
				<label>Cassie</label>
				<styleGender>Female</styleGender>
				<texPath>Modules/Pawns/Hair/Media/Games/Cassie/Cassie</texPath>
				<defName>TMM_Hair_Cassie</defName>
				<category>Soldier</category>
				<hairTags>
					<li>Urban</li>
					<li>Rural</li>
					<li>Soldier</li>
				</hairTags>
			</HairDef>
		<!-- CAVEIRA -->
			<HairDef>
				<label>Caveira</label>
				<styleGender>Female</styleGender>
				<texPath>Modules/Pawns/Hair/Media/Games/Caveira/Caveira</texPath>
				<defName>TMM_Hair_Caveira</defName>
				<category>Urban</category>
				<hairTags>
					<li>Urban</li>
					<li>Rural</li>
					<li>Tribal</li>
					<li>Soldier</li>
				</hairTags>
			</HairDef>
		<!-- CHARLY -->
			<HairDef>
				<label>Charly</label>
				<styleGender>FemaleUsually</styleGender>
				<texPath>Modules/Pawns/Hair/Media/Games/Charly/Charly</texPath>
				<defName>TMM_Hair_Charly</defName>
				<category>Urban</category>
				<hairTags>
					<li>Urban</li>
					<li>Rural</li>
					<li>Tribal</li>
					<li>Soldier</li>
				</hairTags>
			</HairDef>
		<!-- CHELL -->
			<HairDef>
				<label>Chell</label>
				<styleGender>Female</styleGender>
				<texPath>Modules/Pawns/Hair/Media/Games/Chell/Chell</texPath>
				<defName>TMM_Hair_Chell</defName>
				<category>Urban</category>
				<hairTags>
					<li>Urban</li>
					<li>Rural</li>
					<li>Tribal</li>
					<li>Soldier</li>
				</hairTags>
			</HairDef>
		<!-- CHLOE -->
			<HairDef>
				<label>Chloe</label>
				<styleGender>Female</styleGender>
				<texPath>Modules/Pawns/Hair/Media/Games/Chloe/Chloe</texPath>
				<defName>TMM_Hair_Chloe</defName>
				<category>Rural</category>
				<hairTags>
					<li>Urban</li>
					<li>Rural</li>
					<li>Tribal</li>
				</hairTags>
			</HairDef>
		<!-- CHRIS -->
			<HairDef>
				<label>Chris</label>
				<styleGender>Male</styleGender>
				<texPath>Modules/Pawns/Hair/Media/Games/Chris/Chris</texPath>
				<defName>TMM_Hair_Chris</defName>
				<category>Urban</category>
				<hairTags>
					<li>Urban</li>
					<li>Rural</li>
				</hairTags>
			</HairDef>
		<!-- CLAIRE -->
			<HairDef>
				<label>Claire</label>
				<styleGender>Female</styleGender>
				<texPath>Modules/Pawns/Hair/Media/Games/Claire/Claire</texPath>
				<defName>TMM_Hair_Claire</defName>
				<category>Urban</category>
				<hairTags>
					<li>Urban</li>
					<li>Rural</li>
				</hairTags>
			</HairDef>
		<!-- CRYING WOLF -->
			<HairDef>
				<label>Crying Wolf</label>
				<styleGender>Female</styleGender>
				<texPath>Modules/Pawns/Hair/Media/Games/CryingWolf/CryingWolf</texPath>
				<defName>TMM_Hair_CryingWolf</defName>
				<category>Urban</category>
				<hairTags>
					<li>Urban</li>
					<li>Rural</li>
					<li>Tribal</li>
				</hairTags>
			</HairDef>
		<!-- DAD -->
			<HairDef>
				<label>Dad</label>
				<styleGender>Male</styleGender>
				<texPath>Modules/Pawns/Hair/Media/Games/Dad/DadHair</texPath>
				<defName>TMM_Hair_DadHair</defName>
				<category>Urban</category>
				<hairTags>
					<li>Urban</li>
					<li>Rural</li>
				</hairTags>
			</HairDef>
		<!-- DINA -->
			<HairDef>
				<label>Dina</label>
				<styleGender>Female</styleGender>
				<texPath>Modules/Pawns/Hair/Media/Games/Dina/Dina</texPath>
				<defName>TMM_Hair_Dina</defName>
				<category>Urban</category>
				<hairTags>
					<li>Urban</li>
					<li>Rural</li>
					<li>Tribal</li>
					<li>Soldier</li>
				</hairTags>
			</HairDef>
		<!-- DOKAEBBI -->
			<HairDef>
				<label>Dokaebbi</label>
				<styleGender>Female</styleGender>
				<texPath>Modules/Pawns/Hair/Media/Games/Dokaebbi/Dokaebbi</texPath>
				<defName>TMM_Hair_Dokaebbi</defName>
				<category>Urban</category>
				<hairTags>
					<li>Urban</li>
					<li>Rural</li>
					<li>Tribal</li>
				</hairTags>
			</HairDef>
		<!-- DOMINO -->
			<HairDef>
				<label>Domino</label>
				<styleGender>Female</styleGender>
				<texPath>Modules/Pawns/Hair/Media/Games/Domino/Domino</texPath>
				<defName>TMM_Hair_Domino</defName>
				<category>Soldier</category>
				<hairTags>
					<li>Urban</li>
					<li>Rural</li>
					<li>Tribal</li>
					<li>Soldier</li>
				</hairTags>
			</HairDef>
		<!-- ELA -->
			<HairDef>
				<label>Ela</label>
				<styleGender>Female</styleGender>
				<texPath>Modules/Pawns/Hair/Media/Games/Ela/Ela</texPath>
				<defName>TMM_Hair_Ela</defName>
				<category>Urban</category>
				<hairTags>
					<li>Urban</li>
					<li>Rural</li>
				</hairTags>
			</HairDef>
		<!-- ELENA -->
			<HairDef>
				<label>Elena</label>
				<styleGender>Female</styleGender>
				<texPath>Modules/Pawns/Hair/Media/Games/Elena/Elena</texPath>
				<defName>TMM_Hair_Elena</defName>
				<category>Urban</category>
				<hairTags>
					<li>Urban</li>
					<li>Rural</li>
				</hairTags>
			</HairDef>
		<!-- ELIZABETH -->
			<HairDef>
				<label>Elizabeth</label>
				<styleGender>Female</styleGender>
				<texPath>Modules/Pawns/Hair/Media/Games/Elizabeth/Elizabeth</texPath>
				<defName>TMM_Hair_Elizabeth</defName>
				<category>Urban</category>
				<hairTags>
					<li>Urban</li>
					<li>Rural</li>
					<li>Tribal</li>
				</hairTags>
			</HairDef>
		<!-- ELLIE -->
			<HairDef>
				<label>Ellie</label>
				<styleGender>Female</styleGender>
				<texPath>Modules/Pawns/Hair/Media/Games/Ellie/Ellie</texPath>
				<defName>TMM_Hair_Ellie</defName>
				<category>Rural</category>
				<hairTags>
					<li>Urban</li>
					<li>Rural</li>
					<li>Tribal</li>
					<li>Soldier</li>
				</hairTags>
			</HairDef>
		<!-- ELLIE ALT -->
			<HairDef>
				<label>Ellie Alt</label>
				<styleGender>Female</styleGender>
				<texPath>Modules/Pawns/Hair/Media/Games/EllieAlt/Ellie_2</texPath>
				<defName>TMM_Hair_EllieAlt</defName>
				<category>Rural</category>
				<hairTags>
					<li>Urban</li>
					<li>Rural</li>
					<li>Tribal</li>
					<li>Soldier</li>
				</hairTags>
			</HairDef>
		<!-- FAITH -->
			<HairDef>
				<label>Faith</label>
				<styleGender>Female</styleGender>
				<texPath>Modules/Pawns/Hair/Media/Games/Faith/Faith</texPath>
				<defName>TMM_Hair_Faith</defName>
				<category>Urban</category>
				<hairTags>
					<li>Urban</li>
					<li>Rural</li>
				</hairTags>
			</HairDef>
		<!-- FARAH -->
			<HairDef>
				<label>Farah</label>
				<styleGender>Female</styleGender>
				<texPath>Modules/Pawns/Hair/Media/Games/Farah/Farah</texPath>
				<defName>TMM_Hair_Farah</defName>
				<category>Urban</category>
				<hairTags>
					<li>Urban</li>
					<li>Rural</li>
					<li>Tribal</li>
					<li>Soldier</li>
				</hairTags>
			</HairDef>
		<!-- GRAY FOX -->
			<HairDef>
				<label>Gray Fox</label>
				<styleGender>Male</styleGender>
				<texPath>Modules/Pawns/Hair/Media/Games/GrayFox/Gray_Fox</texPath>
				<defName>TMM_Hair_GrayFox</defName>
				<category>Urban</category>
				<hairTags>
					<li>Urban</li>
					<li>Rural</li>
				</hairTags>
			</HairDef>
		<!-- HELENA -->
			<HairDef>
				<label>Helena</label>
				<styleGender>Female</styleGender>
				<texPath>Modules/Pawns/Hair/Media/Games/Helena/Helena</texPath>
				<defName>TMM_Hair_Helena</defName>
				<category>Urban</category>
				<hairTags>
					<li>Urban</li>
					<li>Rural</li>
					<li>Tribal</li>
				</hairTags>
			</HairDef>
		<!-- HIDEO -->
			<HairDef>
				<label>Hideo Kojima</label>
				<styleGender>Male</styleGender>
				<texPath>Modules/Pawns/Hair/Media/Games/Hideo/Hideo</texPath>
				<defName>TMM_Hair_Hideo</defName>
				<category>Urban</category>
				<hairTags>
					<li>Urban</li>
					<li>Rural</li>
				</hairTags>
			</HairDef>
		<!-- HUEY -->
			<HairDef>
				<label>Huey</label>
				<styleGender>Male</styleGender>
				<texPath>Modules/Pawns/Hair/Media/Games/Huey/Huey_Emmerich</texPath>
				<defName>TMM_Hair_Huey</defName>
				<category>Urban</category>
				<hairTags>
					<li>Urban</li>
					<li>Rural</li>
				</hairTags>
			</HairDef>
		<!-- IQ -->
			<HairDef>
				<label>IQ</label>
				<styleGender>Female</styleGender>
				<texPath>Modules/Pawns/Hair/Media/Games/IQ/IQ</texPath>
				<defName>TMM_Hair_IQ</defName>
				<category>Urban</category>
				<hairTags>
					<li>Urban</li>
					<li>Rural</li>
				</hairTags>
			</HairDef>
		<!-- ISKRA -->
			<HairDef>
				<label>Iskra</label>
				<styleGender>FemaleUsually</styleGender>
				<texPath>Modules/Pawns/Hair/Media/Games/Iskra/Iskra</texPath>
				<defName>TMM_Hair_Iskra</defName>
				<category>Punk</category>
				<hairTags>
					<li>Urban</li>
					<li>Rural</li>
					<li>Tribal</li>
					<li>Punk</li>
					<li>Soldier</li>
				</hairTags>
			</HairDef>
		<!-- IZZY -->
			<HairDef>
				<label>Izzy</label>
				<styleGender>Female</styleGender>
				<texPath>Modules/Pawns/Hair/Media/Games/Izzy/Izzy</texPath>
				<defName>TMM_Hair_Izzy</defName>
				<category>Urban</category>
				<hairTags>
					<li>Urban</li>
					<li>Rural</li>
					<li>Tribal</li>
				</hairTags>
			</HairDef>
		<!-- JACOB -->
			<HairDef>
				<label>Jacob</label>
				<styleGender>Male</styleGender>
				<texPath>Modules/Pawns/Hair/Media/Games/Jacob/Jacob</texPath>
				<defName>TMM_Hair_Jacob</defName>
				<category>Soldier</category>
				<hairTags>
					<li>Urban</li>
					<li>Rural</li>
					<li>Punk</li>
					<li>Soldier</li>
				</hairTags>
			</HairDef>
		<!-- JILL -->
			<HairDef>
				<label>Jill</label>
				<styleGender>Female</styleGender>
				<texPath>Modules/Pawns/Hair/Media/Games/Jill/Jill</texPath>
				<defName>TMM_Hair_Jill</defName>
				<category>Urban</category>
				<hairTags>
					<li>Urban</li>
					<li>Rural</li>
				</hairTags>
			</HairDef>
		<!-- JILL ALT -->
			<HairDef>
				<label>Jill Alt</label>
				<styleGender>Female</styleGender>
				<texPath>Modules/Pawns/Hair/Media/Games/JillAlt/Jill_Remake</texPath>
				<defName>TMM_Hair_JillAlt</defName>
				<category>Urban</category>
				<hairTags>
					<li>Urban</li>
					<li>Rural</li>
				</hairTags>
			</HairDef>
		<!-- JOEL -->
			<HairDef>
				<label>Joel</label>
				<styleGender>Male</styleGender>
				<texPath>Modules/Pawns/Hair/Media/Games/Joel/Joel</texPath>
				<defName>TMM_Hair_Joel</defName>
				<category>Rural</category>
				<hairTags>
					<li>Urban</li>
					<li>Rural</li>
				</hairTags>
			</HairDef>
		<!-- JOEY -->
			<HairDef>
				<label>Hudson</label>
				<styleGender>Female</styleGender>
				<texPath>Modules/Pawns/Hair/Media/Games/Joey/Joey_Hudson</texPath>
				<defName>TMM_Hair_JoeyHudson</defName>
				<category>Urban</category>
				<hairTags>
					<li>Urban</li>
					<li>Rural</li>
					<li>Soldier</li>
				</hairTags>
			</HairDef>
		<!-- JULI -->
			<HairDef>
				<label>Juli</label>
				<styleGender>Female</styleGender>
				<texPath>Modules/Pawns/Hair/Media/Games/Juli/Juli</texPath>
				<defName>TMM_Hair_Juli</defName>
				<category>Urban</category>
				<hairTags>
					<li>Urban</li>
					<li>Rural</li>
				</hairTags>
			</HairDef>
		<!-- KARA MESSY -->
			<HairDef>
				<label>Kara Messy</label>
				<styleGender>Female</styleGender>
				<texPath>Modules/Pawns/Hair/Media/Games/KaraMessy/Kara</texPath>
				<defName>TMM_Hair_KaraMessy</defName>
				<category>Urban</category>
				<hairTags>
					<li>Urban</li>
					<li>Rural</li>
				</hairTags>
			</HairDef>
		<!-- KARMA -->
			<HairDef>
				<label>Karma</label>
				<styleGender>FemaleUsually</styleGender>
				<texPath>Modules/Pawns/Hair/Media/Games/Karma/Karma</texPath>
				<defName>TMM_Hair_Karma</defName>
				<category>Punk</category>
				<hairTags>
					<li>Urban</li>
					<li>Rural</li>
					<li>Punk</li>
					<li>Tribal</li>
				</hairTags>
			</HairDef>
		<!-- KIDMAN -->
			<HairDef>
				<label>Kidman</label>
				<styleGender>Female</styleGender>
				<texPath>Modules/Pawns/Hair/Media/Games/Kidman/Kidman</texPath>
				<defName>TMM_Hair_Kidman</defName>
				<category>Urban</category>
				<hairTags>
					<li>Urban</li>
					<li>Rural</li>
				</hairTags>
			</HairDef>
		<!-- KITSUNE -->
			<HairDef>
				<label>Kitsune</label>
				<styleGender>Female</styleGender>
				<texPath>Modules/Pawns/Hair/Media/Games/Kitsune/Kitsune</texPath>
				<defName>TMM_Hair_Kitsune</defName>
				<category>Urban</category>
				<hairTags>
					<li>Urban</li>
					<li>Rural</li>
					<li>Tribal</li>
					<li>Punk</li>
				</hairTags>
			</HairDef>
		<!-- LARA -->
			<HairDef>
				<label>Lara</label>
				<styleGender>Female</styleGender>
				<texPath>Modules/Pawns/Hair/Media/Games/Lara/Lara</texPath>
				<defName>TMM_Hair_Lara</defName>
				<category>Rural</category>
					<hairTags>
						<li>Urban</li>
						<li>Rural</li>
						<li>Soldier</li>
					</hairTags>
			</HairDef>
		<!-- LARA ALT -->
			<HairDef>
				<label>Lara Alt</label>
				<styleGender>Female</styleGender>
				<texPath>Modules/Pawns/Hair/Media/Games/LaraAlt/Lara_Survivor</texPath>
				<defName>TMM_Hair_LaraAlt</defName>
				<category>Rural</category>
				<hairTags>
					<li>Urban</li>
					<li>Rural</li>
					<li>Soldier</li>
				</hairTags>
			</HairDef>
		<!-- LASWELL -->
			<HairDef>
				<label>Laswell</label>
				<styleGender>Female</styleGender>
				<texPath>Modules/Pawns/Hair/Media/Games/Laswell/Laswell</texPath>
				<defName>TMM_Hair_Laswell</defName>
				<category>Urban</category>
				<hairTags>
					<li>Urban</li>
					<li>Rural</li>
					<li>Soldier</li>
				</hairTags>
			</HairDef>
		<!-- LAUGHING OCTOPUS -->
			<HairDef>
				<label>Octopus</label>
				<styleGender>Any</styleGender>
				<texPath>Modules/Pawns/Hair/Media/Games/LaughingOctopus/LaughingOctopus</texPath>
				<defName>TMM_Hair_LaughingOctopus</defName>
				<category>Urban</category>
				<hairTags>
					<li>Urban</li>
					<li>Rural</li>
				</hairTags>
			</HairDef>
		<!-- LEON -->
			<HairDef>
				<label>Leon</label>
				<styleGender>Male</styleGender>
				<texPath>Modules/Pawns/Hair/Media/Games/Leon/Leon</texPath>
				<defName>TMM_Hair_Leon</defName>
				<category>Urban</category>
				<hairTags>
					<li>Urban</li>
					<li>Rural</li>
					<li>Punk</li>
				</hairTags>
			</HairDef>
		<!-- MARA -->
			<HairDef>
				<label>Mara</label>
				<styleGender>Female</styleGender>
				<texPath>Modules/Pawns/Hair/Media/Games/Mara/Mara</texPath>
				<defName>TMM_Hair_Mara</defName>
				<category>Urban</category>
				<hairTags>
					<li>Urban</li>
					<li>Rural</li>
					<li>Tribal</li>
					<li>Soldier</li>
				</hairTags>
			</HairDef>
		<!-- MAXIS -->
			<HairDef>
				<label>Maxis</label>
				<styleGender>Female</styleGender>
				<texPath>Modules/Pawns/Hair/Media/Games/Maxis/Maxis</texPath>
				<defName>TMM_Hair_Maxis</defName>
				<category>Urban</category>
				<hairTags>
					<li>Urban</li>
					<li>Rural</li>
					<li>Tribal</li>
				</hairTags>
			</HairDef>
		<!-- MERYL -->
			<HairDef>
				<label>Meryl</label>
				<styleGender>Female</styleGender>
				<texPath>Modules/Pawns/Hair/Media/Games/Meryl/Meryl</texPath>
				<defName>TMM_Hair_Meryl</defName>
				<category>Soldier</category>
				<hairTags>
					<li>Urban</li>
					<li>Rural</li>
					<li>Soldier</li>
				</hairTags>
			</HairDef>
		<!-- MILLER -->
			<HairDef>
				<label>Miller</label>
				<styleGender>MaleUsually</styleGender>
				<texPath>Modules/Pawns/Hair/Media/Games/Miller/Miller</texPath>
				<defName>TMM_Hair_Miller</defName>
				<category>Urban</category>
				<hairTags>
					<li>Urban</li>
					<li>Rural</li>
				</hairTags>
			</HairDef>
		<!-- NADINE -->
			<HairDef>
				<label>Nadine</label>
				<styleGender>Female</styleGender>
				<texPath>Modules/Pawns/Hair/Media/Games/Nadine/Nadine</texPath>
				<defName>TMM_Hair_Nadine</defName>
				<category>Urban</category>
				<hairTags>
					<li>Urban</li>
					<li>Rural</li>
					<li>Tribal</li>
				</hairTags>
			</HairDef>
		<!-- PARK -->
			<HairDef>
				<label>Park</label>
				<styleGender>Female</styleGender>
				<texPath>Modules/Pawns/Hair/Media/Games/Park/Park</texPath>
				<defName>TMM_Hair_Park</defName>
				<category>Urban</category>
				<hairTags>
					<li>Urban</li>
					<li>Rural</li>
					<li>Tribal</li>
				</hairTags>
			</HairDef>
		<!-- PAZ -->
			<HairDef>
				<label>Paz</label>
				<styleGender>Female</styleGender>
				<texPath>Modules/Pawns/Hair/Media/Games/Paz/Paz</texPath>
				<defName>TMM_Hair_Paz</defName>
				<category>Urban</category>
				<hairTags>
					<li>Urban</li>
					<li>Rural</li>
					<li>Tribal</li>
				</hairTags>
			</HairDef>
		<!-- PORTNOVA -->
			<HairDef>
				<label>Portnova</label>
				<styleGender>Female</styleGender>
				<texPath>Modules/Pawns/Hair/Media/Games/Portnova/Portnova</texPath>
				<defName>TMM_Hair_Portnova</defName>
				<category>Urban</category>
				<hairTags>
					<li>Urban</li>
					<li>Rural</li>
					<li>Soldier</li>
				</hairTags>
			</HairDef>
		<!-- POWER GIRL -->
			<HairDef>
				<label>Power Girl</label>
				<styleGender>Female</styleGender>
				<texPath>Modules/Pawns/Hair/Media/Games/PowerGirl/PowerGirl</texPath>
				<defName>TMM_Hair_PowerGirl</defName>
				<category>Urban</category>
				<hairTags>
					<li>Urban</li>
					<li>Rural</li>
					<li>Soldier</li>
				</hairTags>
			</HairDef>
		<!-- QUIET -->
			<HairDef>
				<label>Quiet</label>
				<styleGender>Female</styleGender>
				<texPath>Modules/Pawns/Hair/Media/Games/Quiet/Quiet</texPath>
				<defName>TMM_Hair_Quiet</defName>
				<category>Soldier</category>
				<hairTags>
					<li>Urban</li>
					<li>Rural</li>
					<li>Soldier</li>
				</hairTags>
			</HairDef>
		<!-- RAGING RAVEN -->
			<HairDef>
				<label>Raven</label>
				<styleGender>Any</styleGender>
				<texPath>Modules/Pawns/Hair/Media/Games/RagingRaven/RagingRaven</texPath>
				<defName>TMM_Hair_RagingRaven</defName>
				<category>Urban</category>
				<hairTags>
					<li>Urban</li>
					<li>Rural</li>
					<li>Tribal</li>
				</hairTags>
			</HairDef>
		<!-- RAIDEN -->
			<HairDef>
				<label>Raiden</label>
				<styleGender>MaleUsually</styleGender>
				<texPath>Modules/Pawns/Hair/Media/Games/Raiden/Raiden</texPath>
				<defName>TMM_Hair_Raiden</defName>
				<category>Urban</category>
				<hairTags>
					<li>Urban</li>
					<li>Rural</li>
				</hairTags>
			</HairDef>
		<!-- RAMIREZ -->
			<HairDef>
				<label>Ramirez</label>
				<styleGender>Female</styleGender>
				<texPath>Modules/Pawns/Hair/Media/Games/Ramirez/Ramirez</texPath>
				<defName>TMM_Hair_Ramirez</defName>
				<category>Soldier</category>
				<hairTags>
					<li>Urban</li>
					<li>Rural</li>
					<li>Soldier</li>
				</hairTags>
			</HairDef>
		<!-- RIVAS -->
			<HairDef>
				<label>Rivas</label>
				<styleGender>Female</styleGender>
				<texPath>Modules/Pawns/Hair/Media/Games/Rivas/Rivas</texPath>
				<defName>TMM_Hair_Rivas</defName>
				<category>Tribal</category>
				<hairTags>
					<li>Urban</li>
					<li>Rural</li>
					<li>Tribal</li>
				</hairTags>
			</HairDef>
		<!-- SCARLET -->
			<HairDef>
				<label>Scarlet</label>
				<styleGender>Female</styleGender>
				<texPath>Modules/Pawns/Hair/Media/Games/Scarlet/Scarlet</texPath>
				<defName>TMM_Hair_Scarlet</defName>
				<category>Punk</category>
				<hairTags>
					<li>Urban</li>
					<li>Rural</li>
					<li>Tribal</li>
					<li>Punk</li>
				</hairTags>
			</HairDef>
		<!-- SCOTT -->
			<HairDef>
				<label>Scott</label>
				<styleGender>Male</styleGender>
				<texPath>Modules/Pawns/Hair/Media/Games/Scott/Scott</texPath>
				<defName>TMM_Hair_Scott</defName>
				<category>Soldier</category>
				<hairTags>
					<li>Urban</li>
					<li>Rural</li>
				</hairTags>
			</HairDef>
		<!-- SCREAMING MANTIS -->
			<HairDef>
				<label>Mantis</label>
				<styleGender>Any</styleGender>
				<texPath>Modules/Pawns/Hair/Media/Games/ScreamingMantis/ScreamingMantis</texPath>
				<defName>TMM_Hair_ScreamingMantis</defName>
				<category>Urban</category>
				<hairTags>
					<li>Urban</li>
					<li>Rural</li>
					<li>Tribal</li>
				</hairTags>
			</HairDef>
		<!-- SHERRY -->
			<HairDef>
				<label>Sherry</label>
				<styleGender>Any</styleGender>
				<texPath>Modules/Pawns/Hair/Media/Games/Sherry/Sherry</texPath>
				<defName>TMM_Hair_Sherry</defName>
				<category>Urban</category>
				<hairTags>
					<li>Urban</li>
					<li>Rural</li>
					<li>Tribal</li>
				</hairTags>
			</HairDef>
		<!-- SHEVA -->
			<HairDef>
				<label>Sheva</label>
				<styleGender>Female</styleGender>
				<texPath>Modules/Pawns/Hair/Media/Games/Sheva/Sheva</texPath>
				<defName>TMM_Hair_Sheva</defName>
				<category>Urban</category>
				<hairTags>
					<li>Urban</li>
					<li>Rural</li>
					<li>Tribal</li>
				</hairTags>
			</HairDef>
		<!-- SOLID SNAKE -->
			<HairDef>
				<label>Solid Snake</label>
				<styleGender>Male</styleGender>
				<texPath>Modules/Pawns/Hair/Media/Games/SolidSnake/Solid_Snake</texPath>
				<defName>TMM_Hair_SolidSnake</defName>
				<category>Urban</category>
				<hairTags>
					<li>Urban</li>
					<li>Rural</li>
				</hairTags>
			</HairDef>
		<!-- SOLID SNAKE ALT -->
			<HairDef>
				<label>Solid Snake Alt</label>
				<styleGender>Male</styleGender>
				<texPath>Modules/Pawns/Hair/Media/Games/SolidSnakeAlt/Solid_Snake_2</texPath>
				<defName>TMM_Hair_SolidSnakeAlt</defName>
				<category>Urban</category>
				<hairTags>
					<li>Urban</li>
					<li>Rural</li>
				</hairTags>
			</HairDef>
		<!-- TANYA -->
			<HairDef>
				<label>Tanya</label>
				<styleGender>Female</styleGender>
				<texPath>Modules/Pawns/Hair/Media/Games/Tanya/Tanya</texPath>
				<defName>TMM_Hair_Tanya</defName>
				<category>Urban</category>
				<hairTags>
					<li>Urban</li>
					<li>Rural</li>
				</hairTags>
			</HairDef>
		<!-- VENOM SNAKE -->
			<HairDef>
				<label>Venom Snake</label>
				<styleGender>Male</styleGender>
				<texPath>Modules/Pawns/Hair/Media/Games/VenomSnake/VenomSnake</texPath>
				<defName>TMM_Hair_Venom_Snake</defName>
				<category>Urban</category>
				<hairTags>
					<li>Urban</li>
					<li>Rural</li>
				</hairTags>
			</HairDef>
		<!-- WALLABY -->
			<HairDef>
				<label>Wallaby</label>
				<styleGender>Female</styleGender>
				<texPath>Modules/Pawns/Hair/Media/Games/Wallaby/Wallaby</texPath>
				<defName>TMM_Hair_Wallaby</defName>
				<category>Soldier</category>
				<hairTags>
					<li>Urban</li>
					<li>Rural</li>
					<li>Soldier</li>
				</hairTags>
			</HairDef>
		<!-- WRAITH -->
			<HairDef>
				<label>Wraith</label>
				<styleGender>Female</styleGender>
				<texPath>Modules/Pawns/Hair/Media/Games/Wraith/Wraith</texPath>
				<defName>TMM_Hair_Wraith</defName>
				<category>Tribal</category>
				<hairTags>
					<li>Urban</li>
					<li>Punk</li>
					<li>Rural</li>
					<li>Tribal</li>
					<li>Soldier</li>
				</hairTags>
			</HairDef>
	<!-- MOVIES -->
		<!-- BARRY -->
			<HairDef>
				<label>Barry</label>
				<styleGender>Male</styleGender>
				<texPath>Modules/Pawns/Hair/Media/Movies/Barry/Barry</texPath>
				<defName>TMM_Hair_Barry</defName>
				<category>Urban</category>
				<hairTags>
					<li>Urban</li>
					<li>Rural</li>
				</hairTags>
			</HairDef>
		<!-- BATEMAN -->
			<HairDef>
				<label>Bateman</label>
				<styleGender>Male</styleGender>
				<texPath>Modules/Pawns/Hair/Media/Movies/Bateman/Bateman</texPath>
				<defName>TMM_Hair_Bateman</defName>
				<category>Urban</category>
				<hairTags>
					<li>Urban</li>
					<li>Rural</li>
				</hairTags>
			</HairDef>
		<!-- BLACK WIDOW -->
			<HairDef>
				<label>Black Widow</label>
				<styleGender>Female</styleGender>
				<texPath>Modules/Pawns/Hair/Media/Movies/BlackWidow/Scarlett</texPath>
				<defName>TMM_Hair_BlackWidow</defName>
				<category>Urban</category>
				<hairTags>
					<li>Urban</li>
					<li>Rural</li>
					<li>Tribal</li>
				</hairTags>
			</HairDef>
		<!-- BLACK WIDOW ALT -->
			<HairDef>
				<label>Black Widow Alt</label>
				<styleGender>Female</styleGender>
				<texPath>Modules/Pawns/Hair/Media/Movies/BlackWidowAlt/BlackWidow_A</texPath>
				<defName>TMM_Hair_BlackWidowAlt</defName>
				<category>Urban</category>
				<hairTags>
					<li>Urban</li>
					<li>Rural</li>
					<li>Tribal</li>
				</hairTags>
			</HairDef>
		<!-- BOND -->
			<HairDef>
				<label>Bond</label>
				<styleGender>Male</styleGender>
				<texPath>Modules/Pawns/Hair/Media/Movies/Bond/Bond</texPath>
				<defName>TMM_Hair_Bond</defName>
				<category>Urban</category>
				<hairTags>
					<li>Urban</li>
					<li>Rural</li>
				</hairTags>
			</HairDef>
		<!-- CHIGURGH -->
			<HairDef>
				<label>Chigurh</label>
				<styleGender>MaleUsually</styleGender>
				<texPath>Modules/Pawns/Hair/Media/Movies/Chigurh/Chigurh</texPath>
				<defName>TMM_Hair_Chigurh</defName>
				<category>Rural</category>
				<hairTags>
					<li>Urban</li>
					<li>Rural</li>
				</hairTags>
			</HairDef>
		<!-- DURDEN -->
			<HairDef>
				<label>Durden</label>
				<styleGender>Male</styleGender>
				<texPath>Modules/Pawns/Hair/Media/Movies/Durden/T_Durden</texPath>
				<defName>TMM_Hair_Durden</defName>
				<category>Urban</category>
				<hairTags>
					<li>Urban</li>
					<li>Rural</li>
				</hairTags>
			</HairDef>
		<!-- EPHRAIM -->
			<HairDef>
				<label>Ephraim</label>
				<styleGender>MaleUsually</styleGender>
				<texPath>Modules/Pawns/Hair/Media/Movies/Ephraim/Efraim</texPath>
				<defName>TMM_Hair_Ephraim</defName>
				<category>Urban</category>
				<hairTags>
					<li>Urban</li>
					<li>Rural</li>
				</hairTags>
			</HairDef>
		<!-- GWENPOOL -->
			<HairDef>
				<label>Gwenpool</label>
				<styleGender>Female</styleGender>
				<texPath>Modules/Pawns/Hair/Media/Movies/Gwenpool/GwenpoolHair</texPath>
				<defName>TMM_Hair_Gwenpool</defName>
				<category>Urban</category>
				<hairTags>
					<li>Urban</li>
					<li>Rural</li>
					<li>Punk</li>
					<li>Tribal</li>
				</hairTags>
			</HairDef>
		<!-- HANS -->
			<HairDef>
				<label>Hans</label>
				<styleGender>Male</styleGender>
				<texPath>Modules/Pawns/Hair/Media/Movies/Hans/Hans_Landa</texPath>
				<defName>TMM_Hair_Hans</defName>
				<category>Urban</category>
				<hairTags>
					<li>Urban</li>
					<li>Rural</li>
				</hairTags>
			</HairDef>
		<!-- MAY -->
			<HairDef>
				<label>May</label>
				<styleGender>Female</styleGender>
				<texPath>Modules/Pawns/Hair/Media/Movies/May/May</texPath>
				<defName>TMM_Hair_May</defName>
				<category>Urban</category>
				<hairTags>
					<li>Urban</li>
					<li>Rural</li>
					<li>Tribal</li>
				</hairTags>
			</HairDef>
		<!-- MAZUR -->
			<HairDef>
				<label>Mazur</label>
				<styleGender>Male</styleGender>
				<texPath>Modules/Pawns/Hair/Media/Movies/Mazur/Mazur</texPath>
				<defName>TMM_Hair_Mazur</defName>
				<category>Urban</category>
				<hairTags>
					<li>Urban</li>
					<li>Rural</li>
				</hairTags>
			</HairDef>
		<!-- MCCLANE -->
			<HairDef>
				<label>McClane</label>
				<styleGender>Male</styleGender>
				<texPath>Modules/Pawns/Hair/Media/Movies/McClane/McClane</texPath>
				<defName>TMM_Hair_McClane</defName>
				<category>Urban</category>
				<hairTags>
					<li>Urban</li>
					<li>Rural</li>
				</hairTags>
			</HairDef>
		<!-- NOBODY -->
			<HairDef>
				<label>Nobody</label>
				<styleGender>Male</styleGender>
				<texPath>Modules/Pawns/Hair/Media/Movies/Nobody/Nobody</texPath>
				<defName>TMM_Hair_Nobody</defName>
				<category>Urban</category>
				<hairTags>
					<li>Urban</li>
					<li>Rural</li>
				</hairTags>
			</HairDef>
		<!-- ORLOV -->
			<HairDef>
				<label>Orlov</label>
				<styleGender>Male</styleGender>
				<texPath>Modules/Pawns/Hair/Media/Movies/Orlov/Orlov</texPath>
				<defName>TMM_Hair_Orlov</defName>
				<category>Urban</category>
				<hairTags>
					<li>Urban</li>
					<li>Rural</li>
				</hairTags>
			</HairDef>
		<!-- PARKER -->
			<HairDef>
				<label>Parker</label>
				<styleGender>Any</styleGender>
				<texPath>Modules/Pawns/Hair/Media/Movies/Parker/Parker</texPath>
				<defName>TMM_Hair_Parker</defName>
				<category>Urban</category>
				<hairTags>
					<li>Urban</li>
					<li>Rural</li>
				</hairTags>
			</HairDef>
		<!-- PUNISHER -->
			<HairDef>
				<label>Punisher</label>
				<styleGender>Male</styleGender>
				<texPath>Modules/Pawns/Hair/Media/Movies/Punisher/Punisher</texPath>
				<defName>TMM_Hair_Punisher</defName>
				<category>Soldier</category>
				<hairTags>
					<li>Urban</li>
					<li>Rural</li>
					<li>Soldier</li>
				</hairTags>
			</HairDef>
		<!-- RAMBO -->
			<HairDef>
				<label>Rambo</label>
				<styleGender>Any</styleGender>
				<texPath>Modules/Pawns/Hair/Media/Movies/Rambo/Rambo</texPath>
				<defName>TMM_Hair_Rambo</defName>
				<category>Rural</category>
				<hairTags>
					<li>Urban</li>
					<li>Rural</li>
					<li>HairLong</li>
				</hairTags>
			</HairDef>
		<!-- SASHA -->
			<HairDef>
				<label>Sasha</label>
				<styleGender>MaleUsually</styleGender>
				<texPath>Modules/Pawns/Hair/Media/Movies/Sasha/Sasha</texPath>
				<defName>TMM_Hair_Sasha</defName>
				<category>Urban</category>
				<hairTags>
					<li>Urban</li>
					<li>Rural</li>
					<li>Soldier</li>
				</hairTags>
			</HairDef>
		<!-- SCARFACE -->
			<HairDef>
				<label>Scarface</label>
				<styleGender>MaleUsually</styleGender>
				<texPath>Modules/Pawns/Hair/Media/Movies/Scarface/Scarface</texPath>
				<defName>TMM_Hair_Scarface</defName>
				<category>Urban</category>
				<hairTags>
					<li>Urban</li>
					<li>Rural</li>
				</hairTags>
			</HairDef>
		<!-- SILVER SABLE -->
			<HairDef>
				<label>Silver Sable</label>
				<styleGender>Female</styleGender>
				<texPath>Modules/Pawns/Hair/Media/Movies/SilverSable/SilverSable</texPath>
				<defName>TMM_Hair_SilverSable</defName>
				<category>Urban</category>
				<hairTags>
					<li>Urban</li>
					<li>Rural</li>
					<li>Punk</li>
					<li>Tribal</li>
				</hairTags>
			</HairDef>
		<!-- STIGLITZ -->
			<HairDef>
				<label>Stiglitz</label>
				<styleGender>Male</styleGender>
				<texPath>Modules/Pawns/Hair/Media/Movies/Stiglitz/Stiglitz</texPath>
				<defName>TMM_Hair_Stiglitz</defName>
				<category>Urban</category>
				<hairTags>
					<li>Urban</li>
					<li>Rural</li>
				</hairTags>
			</HairDef>
		<!-- TERMINATOR -->
			<HairDef>
				<label>Terminator</label>
				<styleGender>Male</styleGender>
				<texPath>Modules/Pawns/Hair/Media/Movies/Terminator/Terminator</texPath>
				<defName>TMM_Hair_Terminator</defName>
				<category>Urban</category>
				<hairTags>
					<li>Urban</li>
					<li>Rural</li>
				</hairTags>
			</HairDef>
		<!-- WICK -->
			<HairDef>
				<label>Wick</label>
				<styleGender>Male</styleGender>
				<texPath>Modules/Pawns/Hair/Media/Movies/Wick/John_Wick</texPath>
				<defName>TMM_Hair_Wick</defName>
				<category>Urban</category>
				<hairTags>
					<li>Urban</li>
					<li>Rural</li>
					<li>HairLong</li>
				</hairTags>
			</HairDef>
		<!-- WOLVERINE -->
			<HairDef>
				<label>Wolverine</label>
				<styleGender>Male</styleGender>
				<texPath>Modules/Pawns/Hair/Media/Movies/Wolverine/Wolverine</texPath>
				<defName>TMM_Hair_Wolverine</defName>
				<category>Soldier</category>
				<hairTags>
					<li>Urban</li>
					<li>Rural</li>
					<li>Soldier</li>
				</hairTags>
			</HairDef>
		<!-- ZOLLER -->
			<HairDef>
				<label>Zoller</label>
				<styleGender>Male</styleGender>
				<texPath>Modules/Pawns/Hair/Media/Movies/Zoller/Zoller</texPath>
				<defName>TMM_Hair_Zoller</defName>
				<category>Urban</category>
				<hairTags>
					<li>Urban</li>
					<li>Rural</li>
				</hairTags>
			</HairDef>
	<!-- TV -->
		<!-- BEBOP -->
			<HairDef>
				<label>Bebop</label>
				<styleGender>Any</styleGender>
				<texPath>Modules/Pawns/Hair/Media/TV/Bebop/Spike</texPath>
				<defName>TMM_Hair_Bebop</defName>
				<category>Urban</category>
				<hairTags>
					<li>Urban</li>
					<li>Rural</li>
				</hairTags>
			</HairDef>
		<!-- BILLY -->
			<HairDef>
				<label>Billy</label>
				<styleGender>Male</styleGender>
				<texPath>Modules/Pawns/Hair/Media/TV/Billy/Billy_H</texPath>
				<defName>TMM_Hair_Billy</defName>
				<category>Urban</category>
				<hairTags>
					<li>Urban</li>
					<li>Rural</li>
				</hairTags>
			</HairDef>
		<!-- BUTCHER -->
			<HairDef>
				<label>Butcher</label>
				<styleGender>Male</styleGender>
				<texPath>Modules/Pawns/Hair/Media/TV/Butcher/Butcher</texPath>
				<defName>TMM_Hair_Butcher</defName>
				<category>Urban</category>
				<hairTags>
					<li>Urban</li>
					<li>Rural</li>
				</hairTags>
			</HairDef>
		<!-- HOMELANDER -->
			<HairDef>
				<label>Homelander</label>
				<styleGender>Male</styleGender>
				<texPath>Modules/Pawns/Hair/Media/TV/Homelander/Homelander</texPath>
				<defName>TMM_Hair_Homelander</defName>
				<category>Urban</category>
				<hairTags>
					<li>Urban</li>
					<li>Rural</li>
				</hairTags>
			</HairDef>
		<!-- INVINCIBLE -->
			<HairDef>
				<label>Invincible</label>
				<styleGender>Male</styleGender>
				<texPath>Modules/Pawns/Hair/Media/TV/Invincible/Invincible</texPath>
				<defName>TMM_Hair_Invincible</defName>
				<category>Urban</category>
				<hairTags>
					<li>Urban</li>
					<li>Rural</li>
				</hairTags>
			</HairDef>
		<!-- JAMESON -->
			<HairDef>
				<label>Jameson</label>
				<styleGender>Male</styleGender>
				<texPath>Modules/Pawns/Hair/Media/TV/Jameson/J_Jameson</texPath>
				<defName>TMM_Hair_Jameson</defName>
				<category>Urban</category>
				<hairTags>
					<li>Urban</li>
					<li>Rural</li>
				</hairTags>
			</HairDef>
		<!-- MULDER -->
			<HairDef>
				<label>Mulder</label>
				<styleGender>Male</styleGender>
				<texPath>Modules/Pawns/Hair/Media/TV/Mulder/Mulder</texPath>
				<defName>TMM_Hair_Mulder</defName>
				<category>Urban</category>
				<hairTags>
					<li>Urban</li>
					<li>Rural</li>
				</hairTags>
			</HairDef>
		<!-- OMNIMAN -->
			<HairDef>
				<label>Omniman</label>
				<styleGender>Male</styleGender>
				<texPath>Modules/Pawns/Hair/Media/TV/Omniman/Omniman</texPath>
				<defName>TMM_Hair_Omniman</defName>
				<category>Urban</category>
				<hairTags>
					<li>Urban</li>
					<li>Rural</li>
				</hairTags>
			</HairDef>
		<!-- SCULLY -->
			<HairDef>
				<label>Scully</label>
				<styleGender>Female</styleGender>
				<texPath>Modules/Pawns/Hair/Media/TV/Scully/Scully</texPath>
				<defName>TMM_Hair_Scully</defName>
				<category>Urban</category>
				<hairTags>
					<li>Urban</li>
					<li>Rural</li>
					<li>Tribal</li>
				</hairTags>
			</HairDef>
		<!-- TENNANT -->
			<HairDef>
				<label>Tennant</label>
				<styleGender>Male</styleGender>
				<texPath>Modules/Pawns/Hair/Media/TV/Tennant/Tennant</texPath>
				<defName>TMM_Hair_Tennant</defName>
				<category>Urban</category>
				<hairTags>
					<li>Urban</li>
					<li>Rural</li>
					<li>Soldier</li>
				</hairTags>
			</HairDef>
		<!-- VELMA -->
			<HairDef>
				<label>Velma</label>
				<styleGender>Female</styleGender>
				<texPath>Modules/Pawns/Hair/Media/TV/Velma/Velma</texPath>
				<defName>TMM_Hair_Velma</defName>
				<category>Punk</category>
				<hairTags>
					<li>Urban</li>
					<li>Rural</li>
					<li>Tribal</li>
					<li>Punk</li>
				</hairTags>
			</HairDef>
</Defs>