<?xml version="1.0" encoding="utf-8" ?>
<Defs>
	<HugsLib.UpdateFeatureDef Abstract="true" Name="MO_Stuff_UpdateBase">
		<modNameReadable>Medieval Overhaul Toggable Stuff</modNameReadable>
		<modIdentifier>Accurex.MedievalOverhaul.Stuff</modIdentifier>
		<linkUrl>https://steamcommunity.com/sharedfiles/filedetails/?id=2898440531</linkUrl>
	</HugsLib.UpdateFeatureDef>
	
	<HugsLib.UpdateFeatureDef ParentName="MO_Stuff_UpdateBase">
		<defName>MOTS_Mineables</defName>
		<assemblyVersion>0.1</assemblyVersion>
		<content>I have added a function to restore the vanilla map generation. So you can toggle the generation of vanilla mineables during map creation.
However, you have to restart the game after you have activated it.</content>
	</HugsLib.UpdateFeatureDef>
	
	<HugsLib.UpdateFeatureDef ParentName="MO_Stuff_UpdateBase">
		<defName>MOTS_MOUpdate_FuelFilters</defName>
		<assemblyVersion>0.2</assemblyVersion>
		<content>Due to the MO update, I have had to adjust the fuel filters. 
Also, the DrawOffSet function has been removed as it is now part of MO.</content>
	</HugsLib.UpdateFeatureDef>
	
	<HugsLib.UpdateFeatureDef ParentName="MO_Stuff_UpdateBase">
		<defName>MOTS_MOUpdate_AnimalHoods</defName>
		<assemblyVersion>0.3</assemblyVersion>
		<content>This function is deactivated by default. If it is activated, the animal helmets (grizzly bear, polar bear, arctic wolf, timber wolf) can be worn over the regular helmets.|img:pics/221213</content>
	</HugsLib.UpdateFeatureDef>
	
	<HugsLib.UpdateFeatureDef ParentName="MO_Stuff_UpdateBase">
		<defName>MOTS_MOUpdate_WoodMechanic</defName>
		<assemblyVersion>0.4</assemblyVersion>
		<content>The default setting for the Wood Reversal Patch has been changed due to some confusion in the past.
		
Many people subscribe to this mod without reading what it does and then wonder why there is no wood.

Therefore, please check the setting before you save your savegame.</content>
	</HugsLib.UpdateFeatureDef>
</Defs>